textformat/__init__.py
textformat/core.py
textformat-0.0.1.dist-info/LICENSE
textformat-0.0.1.dist-info/METADATA
textformat-0.0.1.dist-info/WHEEL
textformat-0.0.1.dist-info/top_level.txt
textformat-0.0.1.dist-info/RECORD
