Metadata-Version: 2.1
Name: textformat
Version: 0.0.1
Summary: TextFormat is a Python library for data cleaning.
Home-page: https://github.com/LuferGonn/textformat
Author: Luis Fernando
Author-email: lufergonn@gmail.com
License: MIT License
Project-URL: Bug Tracker, https://github.com/LuferGonn/textformat/issues
Project-URL: Source Code, https://github.com/LuferGonn/textformat
Keywords: Textformat,Data cleaning
Platform: any
Classifier: License :: OSI Approved :: MIT License
Classifier: Operating System :: OS Independent
Classifier: Programming Language :: Python
Classifier: Programming Language :: Python :: 3
Classifier: Programming Language :: Python :: 3 :: Only
Classifier: Programming Language :: Python :: 3.7
Classifier: Programming Language :: Python :: 3.8
Classifier: Programming Language :: Python :: 3.9
Requires-Python: >=3.6
License-File: LICENSE
Requires-Dist: emoji
